uvve/__init__.py
uvve/__main__.py
uvve/cli.py
uvve/commands/__init__.py
uvve/commands/analytics.py
uvve/commands/azure.py
uvve/commands/environment.py
uvve/commands/maintenance.py
uvve/commands/packages.py
uvve/commands/shell.py
uvve/core/__init__.py
uvve/core/analytics.py
uvve/core/azure.py
uvve/core/freeze.py
uvve/core/manager.py
uvve/core/paths.py
uvve/core/python.py
uvve/core/utils.py
uvve/shell/__init__.py
uvve/shell/activate.py
uvve/shell/completion.py
uvve-1.3.1.dist-info/METADATA
uvve-1.3.1.dist-info/WHEEL
uvve-1.3.1.dist-info/entry_points.txt
uvve-1.3.1.dist-info/licenses/LICENSE
uvve-1.3.1.dist-info/RECORD
