Metadata-Version: 2.4
Name: uvve
Version: 1.3.1
Summary: A CLI tool for managing Python virtual environments using uv
Project-URL: Homepage, https://github.com/hedge-quill/uvve
Project-URL: Repository, https://github.com/hedge-quill/uvve
Project-URL: Issues, https://github.com/hedge-quill/uvve/issues
Author-email: Your Name <your.email@example.com>
License-Expression: MIT
License-File: LICENSE
Classifier: Development Status :: 3 - Alpha
Classifier: Intended Audience :: Developers
Classifier: License :: OSI Approved :: MIT License
Classifier: Programming Language :: Python :: 3
Classifier: Programming Language :: Python :: 3.10
Classifier: Programming Language :: Python :: 3.11
Classifier: Programming Language :: Python :: 3.12
Requires-Python: >=3.10
Requires-Dist: rich>=13.0.0
Requires-Dist: toml>=0.10.2
Requires-Dist: typer>=0.9.0
Provides-Extra: dev
Requires-Dist: black>=23.0.0; extra == 'dev'
Requires-Dist: mypy>=1.0.0; extra == 'dev'
Requires-Dist: pre-commit>=3.0.0; extra == 'dev'
Requires-Dist: pytest-cov>=4.0.0; extra == 'dev'
Requires-Dist: pytest>=7.0.0; extra == 'dev'
Requires-Dist: ruff>=0.1.0; extra == 'dev'
Requires-Dist: types-toml>=0.10.8; extra == 'dev'
